{
    "width": 24,
    "height": 12,
    "assistants":
    {
        "3x1_red":
        {
            "type": "path",
            "emit_sound": "syntom",
            "play_duration": 16,
            "colour": "#ff0000",
            "shadow_colour": "#65393e",
            "speed": 1,
            "nodes":
            {
                "0:0":[1,1,0,0],
                "0:1":[1,0,0,0],
                "0:-1":[0,1,0,0]
            }
        },
        "1x1_yellow":
        {
            "type": "path",
            "emit_sound": "onekick",
            "play_duration": 20,
            "colour": "#ffff00",
            "shadow_colour": "#65793e",
            "speed": 1,
            "nodes":
            {
                "0:0":[0,0,0,0]
            }
        },
        "3x1_magenta":
        {
            "type": "path",
            "emit_sound": "synthbass",
            "play_duration": 32,
            "colour": "#ad61b5",
            "shadow_colour": "#533357",
            "speed": 2,
            "nodes":
            {
                "0:0":[1,1,0,0],
                "0:1":[1,0,0,0],
                "0:-1":[0,1,0,0]
            }
        },
        "4x1_green":
        {
            "type": "path",
            "emit_sound": "ride",
            "play_duration": 16,
            "colour": "#00ff00",
            "shadow_colour": "#006500",
            "speed": 1,
            "nodes":
            {
                "0:1":[1,0,0,0],
                "0:0":[1,1,0,0],
                "0:-1":[1,1,0,0],
                "0:-2":[0,1,0,0]
            }
        }                      
    }, 
    "tracks": 
    {
        "3:6":
        {
            "exits": [0,0,1,0],
            "info": "F"
        },
        "4:6":
        {
            "exits": [0,0,1,1]
        },
        "5:6":
        {
            "exits": [0,0,1,1]
        },
        "6:6":
        {
            "exits": [0,0,1,1]
        },
        "7:6":
        {
            "exits": [0,0,1,1]
        },
        "8:6":
        {
            "exits": [0,0,1,1]
        },
        "9:6":
        {
            "exits": [0,0,1,1]
        },
        "10:6":
        {
            "exits": [1,0,0,1]
        },
        "10:5":
        {
            "exits": [1,1,0,0]
        },
        "10:4":
        {
            "exits": [1,1,0,0]
        },
        "10:3":
        {
            "exits": [0,1,1,0]
        },
        "11:3":
        {
            "exits": [0,1,1,0]
        },
        "12:3":
        {
            "exits": [0,1,1,0]
        },
        "13:3":
        {
            "exits": [0,1,1,0]
        },
        "14:3":
        {
            "exits": [0,1,1,0]
        },
        "15:3":
        {
            "exits": [0,1,1,0]
        },
        "16:3":
        {
            "exits": [0,1,1,0]
        },
        "17:3":
        {
            "exits": [0,1,1,0]
        },
        "18:3":
        {
            "exits": [0,1,1,0]
        },
        "19:3":
        {
            "exits": [0,0,0,0],
            "info": "T"
        }
    }
}